nipype_fsl_anat.py
nipype_fsl_anat-1.0.1.dist-info/LICENSE
nipype_fsl_anat-1.0.1.dist-info/WHEEL
nipype_fsl_anat-1.0.1.dist-info/METADATA
nipype_fsl_anat-1.0.1.dist-info/RECORD
