Metadata-Version: 2.1
Name: nipype-fsl-anat
Version: 1.0.1
Summary: Nipype interface(s) wrapping the `fsl_anat` command line tool
Author: Andrew Ross
Author-email: andrew.ross.mail@gmail.com
Requires-Python: >=3.8,<4.0
Classifier: Programming Language :: Python :: 3
Classifier: Programming Language :: Python :: 3.10
Classifier: Programming Language :: Python :: 3.8
Classifier: Programming Language :: Python :: 3.9
Requires-Dist: nibabel (>=3.0.0,<4.0.0)
Requires-Dist: nipype (>=1.1.0,<2.0.0)
